Workbook

Sheet Assumptions
A1: BremsenTech GmbH ROI Model : Assumptions Tab
A3: Input Variable | B3: Value (EUR / unit) | C3: Notes / Source
A4: Monthly order volume (orders/month) | B4: 85 | C4: BremsenTech operational baseline (fictional)
A5: Average order value (EUR) | B5: 12500 | C5: Based on brake disc unit pricing, ~85K units / ~680 orders per month
A6: Manual data entry error rate (AS-IS) | B6: 0.04 | C6: APQC benchmarking having 4% error rate for manual ERP entry
A7: Manual data entry error rate (TO-BE) | B7: 0.001 | C7: SAP SD automated entry which will shows residual errors <0.1%
A8: Time per manual order entry (minutes) | B8: 23 | C8: Internal BremsenTech process estimate
A9: Average production scheduling delay AS-IS (days) | B9: 2.1 | C9: Excel-based scheduling bottleneck observed in process audit
A10: Average production scheduling delay TO-BE (days) | B10: 0.2 | C10: SAP PP MRP planning run and at same-day scheduling
A11: Defective units shipped 2024 | B11: 340 | C11: BremsenTech quality records, end-of-line detection gap
A12: Average return/rework cost per defective unit (EUR) | B12: 250 | C12: Industry standard automotive warranty/rework cost
A13: AR monthly balance (EUR) | B13: 1300000 | C13: Based on EUR 38M revenue / 12 months * payment terms adjustment
A14: Invoice lag AS-IS (days) | B14: 8.5 | C14: BremsenTech accounts receivable process (measured average)
A15: Invoice lag TO-BE (days) | B15: 0.5 | C15: Automated EDI INVOIC on goods issue confirmation
... A23: Annual expediting cost from scheduling delays (EUR) | B23: 18000 | C23: Carrier premium + overtime estimate from 2.1-day avg delays

Sheet ROI Calculation
A1: BremsenTech GmbH — Annual Cost of Process Gaps & Projected SAP Savings
A3: Gap ID | B3: Gap Title | C3: Calculation Logic | D3: Annual Cost AS-IS (EUR) | E3: Annual Savings TO-BE (EUR) | F3: Residual Cost (EUR) | G3: SAP Fix
A4: G-01 | B4: Zero EDI Integration | C4: Lost BMW Tier-1 opportunity (conservative pipeline) | D4: 4000000 | E4: 4000000 | F4: 0 | G4: SAP SD + Integration Suite (BTP EDI)
A5: G-02 | B5: Manual Order Entry Errors | C5: 85 orders/mo × 4% error rate × EUR 150 rework cost | D5: =Assumptions!B4*12*Assumptions!B6*Assumptions!B22 -> 6120 | E5: =Assumptions!B4*12*(Assumptions!B6-Assumptions!B7)*Assumptions!B22 -> 5967 | F5: =D5-E5 -> 153 | G5: SAP SD — automated PO import (EDI ORDERS)
A6: G-03 | B6: Excel Production Scheduling Delays | C6: Scheduling delay cost + expediting premiums | D6: =Assumptions!B4*12*Assumptions!B9*50+Assumptions!B23 -> 125100 | E6: =Assumptions!B4*12*(Assumptions!B9-Assumptions!B10)*50+Assumptions!B23*0.1 -> 98700 | F6: =D6-E6 -> 26400 | G6: SAP PP — MRP/MPS planning runs
A7: G-04 | B7: End-of-Line Batch QC Detection | C7: 340 defective units × EUR 250 return/rework cost | D7: =Assumptions!B11*Assumptions!B12 -> 85000 | E7: =Assumptions!B11*Assumptions!B12*0.15 -> 12750 | F7: =D7-E7 -> 72250 | G7: SAP QM — inline inspection at each stage
A8: G-05 | B8: Manual Invoice Lag (8.5 days) | C8: AR balance × days lag × cost of capital | D8: =Assumptions!B13*(Assumptions!B14/365)*Assumptions!B16*365 -> 331500 | E8: =Assumptions!B13*(Assumptions!B15/365)*Assumptions!B16*365 -> 19500 | F8: =D8-E8 -> 312000 | G8: SAP FI/AR — automated EDI INVOIC
A9: G-06 | B9: No Delivery Visibility (SLA breach) | C9: Continental SLA penalty clause | D9: =Assumptions!B17 -> 180000 | E9: =Assumptions!B17*0.95 -> 171000 | F9: =D9-E9 -> 9000 | G9: SAP TM / BTP — carrier booking + tracking
A10: G-07 | B10: Fragmented Inventory Data | C10: Excess holding cost from low inventory turns | D10: =(Assumptions!B21-Assumptions!B20)/Assumptions!B20*Assumptions!B18*Assumptions!B19 -> 155555.56 | E10: =(Assumptions!B21-Assumptions!B20)/Assumptions!B20*Assumptions!B18*Assumptions!B19*0.85 -> 132222.22 | F10: =D10-E10 -> 23333.333 | G10: SAP MM + EWM — real-time bin tracking
A11: TOTAL | B11: (excl. EUR 4M+ OEM opportunity) | D11: =SUM(D5:D10) -> 883275.56 | E11: =SUM(E5:E10) -> 440139.22 | F11: =SUM(F5:F10) -> 443136.33
A13: Summary
A14: Gross annual cost of 7 process gaps (excl. EUR 4M opportunity): €683,200
A15: Projected annual savings post SAP S/4HANA implementation: €600,000+

Sheet KPI Dashboard
A1: BremsenTech GmbH — AS-IS vs TO-BE KPI Comparison
A3: KPI Metric | B3: AS-IS (Current) | C3: TO-BE (Target) | D3: Improvement
A4: OtD Cycle Time (days) | B4: 14.2 | C4: 8.1 | D4: =B5-C5 -> -0.09
A5: On-Time Delivery Rate (%) | B5: 0.87 | C5: 0.96 | D5: =C6-B6 -> 5
A6: Inventory Turnover (x / year) | B6: 9 | C6: 14 | D6: =C7-B7 -> -8
A7: Invoice Processing Time (days) | B7: 8.5 | C7: 0.5 | D7: =B8-C8 -> 13
A8: Manual Process Handoffs | B8: 17 | C8: 4 | D8: =B9-C9 -> 600000
A9: Annual Process Cost (EUR) | B9: 683200 | C9: 83200 | D9: =B10-C10 -> -9
A10: On-Time Delivery vs Target (pp gap) | B10: -9 | C10: 0 | D10: =C11-B11 -> 1
A11: EDI Integration Rate (%) | B11: 0 | C11: 1 | D11: =C12-B12 -> 0
